pygeomatch/__init__.py
pygeomatch/geometric_matching_of_areas.py
pygeomatch/match.py
pygeomatch/multi_criteria.py
pygeomatch/multi_criteria2.py
pygeomatch/optimal_transport.py
pygeomatch/py.typed
pygeomatch/radial.py
pygeomatch/util.py
pygeomatch-0.0.2.dist-info/licenses/LICENSE
pygeomatch-0.0.2.dist-info/WHEEL
pygeomatch-0.0.2.dist-info/entry_points.txt
pygeomatch-0.0.2.dist-info/METADATA
pygeomatch-0.0.2.dist-info/RECORD
