Metadata-Version: 2.4
Name: pygeomatch
Version: 0.0.2
Summary: A package to match geographical features
Author: Paul Guardiola, Juste Raimbault, Ana-Maria Raimond, Julien Perret, Nicolas Audebert
Author-email: Paul Guardiola <Paul.Guardiola@ign.fr>, Juste Raimbault <Juste.Raimbault@ign.fr>, Ana-Maria Raimond <Ana-Maria.Raimond@ign.fr>, Julien Perret <Julien.Perret@ign.fr>, Nicolas Audebert <Nicolas.Audebert@ign.fr>
License-Expression: GPL-3.0-or-later
License-File: LICENSE
Classifier: Programming Language :: Python :: 3
Classifier: Operating System :: OS Independent
Requires-Dist: bitarray>=3.8.0
Requires-Dist: geopandas>=1.0.1
Requires-Dist: more-itertools>=10.8.0
Requires-Dist: pot>=0.9.6.post1
Requires-Dist: typer>=0.21.1
Requires-Python: >=3.9
Project-URL: Homepage, https://github.com/umrlastig/pygeomatch/
Project-URL: Issues, https://github.com/umrlastig/pygeomatch/issues
